{
  "parent": "veggiesdelight:main/vd_cauliflower_master",
  "display": {
    "title": {
      "translate": "veggiesdelight.advancement.vd_garlic_master"
    },
    "description": {
      "translate": "veggiesdelight.advancement.vd_garlic_master.desc"
    },
    "icon": {
      "item": "veggiesdelight:garlic_baked_cod"
    },
    "frame": "goal",
    "show_toast": true,
    "announce_to_chat": false,
    "hidden": false
  },
  "criteria": {
    "A": {
      "trigger": "minecraft:inventory_changed",
      "conditions": {
        "items": [{ "items": ["veggiesdelight:fermented_garlic_honey"] }]
      }
    },
    "B": {
      "trigger": "minecraft:inventory_changed",
      "conditions": {
        "items": [{ "items": ["veggiesdelight:garlic_baked_cod"] }]
      }
    },
    "C": {
      "trigger": "minecraft:inventory_changed",
      "conditions": {
        "items": [{ "items": ["veggiesdelight:garlic_bread"] }]
      }
    },
    "D": {
      "trigger": "minecraft:inventory_changed",
      "conditions": {
        "items": [{ "items": ["veggiesdelight:garlic_chicken_stew"] }]
      }
    },
    "E": {
      "trigger": "minecraft:inventory_changed",
      "conditions": {
        "items": [{ "items": ["veggiesdelight:garlic_rice_with_cauliflower"] }]
      }
    },
    "F": {
      "trigger": "minecraft:inventory_changed",
      "conditions": {
        "items": [{ "items": ["veggiesdelight:garlic_stuffed_mushrooms"] }]
      }
    }
  },
  "requirements": [
    ["A"], ["B"], ["C"], ["D"], ["E"], ["F"]
  ],
  "rewards": {
    "experience": 300
  }
}
